minmodapi/__init__.py
minmodapi/__main__.py
minmodapi-1.3.5.dist-info/METADATA
minmodapi-1.3.5.dist-info/WHEEL
minmodapi-1.3.5.dist-info/RECORD
