Metadata-Version: 2.1
Name: minmodapi
Version: 1.3.5
Summary: Client API for the MinMod API
License: MIT
Author: Binh Vu
Author-email: bvu687@gmail.com
Requires-Python: >=3.11,<4.0
Classifier: License :: OSI Approved :: MIT License
Classifier: Programming Language :: Python :: 3
Classifier: Programming Language :: Python :: 3.11
Classifier: Programming Language :: Python :: 3.12
Classifier: Programming Language :: Python :: 3.13
Requires-Dist: httpx (>=0.28.1,<0.29.0)
Requires-Dist: python-slugify (>=8.0.4,<9.0.0)
Requires-Dist: tqdm (>=4.67.1,<5.0.0)
